flake8_formatter_vscode/__init__.py
flake8_formatter_vscode/plugin.py
flake8_formatter_vscode-0.0.1.dist-info/entry_points.txt
flake8_formatter_vscode-0.0.1.dist-info/LICENSE
flake8_formatter_vscode-0.0.1.dist-info/WHEEL
flake8_formatter_vscode-0.0.1.dist-info/METADATA
flake8_formatter_vscode-0.0.1.dist-info/RECORD
