Metadata-Version: 2.1
Name: flake8_formatter_vscode
Version: 0.0.1
Summary: Flake8 formatter.
Keywords: flake8,formatter,vscode
Author-email: Rodolphe Pelloux-Prayer <rodolphe@damsy.net>
Requires-Python: >=3.6
Classifier: License :: OSI Approved :: MIT License
Requires-Dist: flake8
Requires-Dist: black ; extra == "dev"
Requires-Dist: mypy ; extra == "dev"
Requires-Dist: flake8 ; extra == "dev"
Requires-Dist: pytest ; extra == "test"
Requires-Dist: pytest-sugar ; extra == "test"
Project-URL: Source, https://gitlab.com/RoPP/flake8-formatter-vscode
Provides-Extra: dev
Provides-Extra: test
